hoptest/__init__.py
hoptest/hoptest.py
the_hop_test-0.2.0.dist-info/METADATA
the_hop_test-0.2.0.dist-info/WHEEL
the_hop_test-0.2.0.dist-info/entry_points.txt
the_hop_test-0.2.0.dist-info/licenses/LICENSE
the_hop_test-0.2.0.dist-info/RECORD
