Metadata-Version: 2.3
Name: the-hop-test
Version: 0.2.0
Summary: Run the Hop Test against your python code repository
Project-URL: Homepage, https://github.com/hopservices/the-hop-test
Author-email: Mark Flanagan <mflanagan@hoplabs.com>
License-File: LICENSE
Classifier: Operating System :: OS Independent
Classifier: Programming Language :: Python :: 3
Requires-Python: >=3.8
Requires-Dist: bandit>=1.7.8
Requires-Dist: radon>=6.0.1
Requires-Dist: rich>=13.7.1
Requires-Dist: tomli>=1.1.0; python_version < '3.11'
